overity/__init__.py
overity/__main__.py
overity/errors.py
overity/api/__init__.py
overity/backend/__init__.py
overity/backend/bench.py
overity/backend/dataset.py
overity/backend/inference_agent.py
overity/backend/method.py
overity/backend/model.py
overity/backend/program.py
overity/backend/report.py
overity/backend/flow/__init__.py
overity/backend/flow/arguments.py
overity/backend/flow/ctx.py
overity/backend/flow/environment.py
overity/backend/report_view/__init__.py
overity/backend/report_view/simple_server.py
overity/backend/report_view/topt_html.py
overity/bench/__init__.py
overity/bench/abstraction.py
overity/exchange/__init__.py
overity/exchange/bench_toml.py
overity/exchange/capability_toml.py
overity/exchange/execution_target_toml.py
overity/exchange/program_toml.py
overity/exchange/report_json.py
overity/exchange/bench_abstraction/description_md.py
overity/exchange/bench_abstraction/file_py.py
overity/exchange/dataset_package/__init__.py
overity/exchange/dataset_package/metadata.py
overity/exchange/dataset_package/package.py
overity/exchange/inference_agent_package/__init__.py
overity/exchange/inference_agent_package/metadata.py
overity/exchange/inference_agent_package/package.py
overity/exchange/method_common/__init__.py
overity/exchange/method_common/description_md.py
overity/exchange/method_common/file_ipynb.py
overity/exchange/method_common/file_py.py
overity/exchange/model_package_v1/__init__.py
overity/exchange/model_package_v1/metadata.py
overity/exchange/model_package_v1/package.py
overity/frontend/__init__.py
overity/frontend/types.py
overity/frontend/bench/__init__.py
overity/frontend/bench/list_abstractions_cmd.py
overity/frontend/bench/list_cmd.py
overity/frontend/dataset/__init__.py
overity/frontend/dataset/list_cmd.py
overity/frontend/inference_agent/__init__.py
overity/frontend/inference_agent/list_cmd.py
overity/frontend/method/__init__.py
overity/frontend/method/list_cmd.py
overity/frontend/method/run_cmd.py
overity-0.0.5.dist-info/METADATA
overity-0.0.5.dist-info/WHEEL
overity-0.0.5.dist-info/entry_points.txt
overity-0.0.5.dist-info/licenses/LICENSE
overity-0.0.5.dist-info/RECORD
