Metadata-Version: 2.4
Name: overity
Version: 0.0.5
Summary: MLOps oriented framework for trustworthy Edge-AI
Project-URL: Documentation, https://overity.ai
Project-URL: Issues, https://github.com/fdmysterious/overity/issues
Project-URL: Source, https://github.com/fdmysterious/overity
Author-email: Florian Dupeyron <florian.dupeyron@elsys-design.com>
License-Expression: Apache-2.0
License-File: LICENSE
Classifier: Programming Language :: Python
Classifier: Programming Language :: Python :: 3.8
Classifier: Programming Language :: Python :: 3.9
Classifier: Programming Language :: Python :: 3.10
Classifier: Programming Language :: Python :: 3.11
Classifier: Programming Language :: Python :: 3.12
Classifier: Programming Language :: Python :: Implementation :: CPython
Classifier: Programming Language :: Python :: Implementation :: PyPy
Requires-Python: >=3.8
Requires-Dist: jinja2==3.1.6
Requires-Dist: jsonschema==4.23.0
Requires-Dist: matplotlib==3.10.8
Requires-Dist: nbformat==5.10.4
Requires-Dist: pandas==2.3.3
Requires-Dist: parsimonious==0.10.0
Requires-Dist: plotly==6.5.1
Requires-Dist: toml==0.10.2
